<?xml version="1.0" encoding="utf-8"?>
<TextureAtlas imagePath="MADNESS-TOM.png">
	<!-- Created with Adobe Animate version 19.2.1.408 -->
	<!-- http://www.adobe.com/products/animate.html -->
	<SubTexture name="TOM DOWN0000" x="0" y="0" width="1280" height="720"/>
	<SubTexture name="TOM DOWN0001" x="0" y="0" width="1280" height="720"/>
	<SubTexture name="TOM DOWN0002" x="1280" y="0" width="1280" height="720"/>
	<SubTexture name="TOM DOWN0003" x="1280" y="0" width="1280" height="720"/>
	<SubTexture name="TOM DOWN0004" x="2560" y="0" width="1280" height="720"/>
	<SubTexture name="TOM DOWN0005" x="2560" y="0" width="1280" height="720"/>
	<SubTexture name="TOM DOWN0006" x="0" y="720" width="1280" height="720"/>
	<SubTexture name="TOM DOWN0007" x="0" y="720" width="1280" height="720"/>
	<SubTexture name="TOM DOWN0008" x="0" y="720" width="1280" height="720"/>
	<SubTexture name="TOM DOWN0009" x="0" y="720" width="1280" height="720"/>
	<SubTexture name="TOM DOWN0010" x="0" y="720" width="1280" height="720"/>
	<SubTexture name="TOM DOWN0011" x="0" y="720" width="1280" height="720"/>
	<SubTexture name="TOM DOWN0012" x="0" y="720" width="1280" height="720"/>
	<SubTexture name="TOM LEFT0000" x="1280" y="720" width="1280" height="720"/>
	<SubTexture name="TOM LEFT0001" x="1280" y="720" width="1280" height="720"/>
	<SubTexture name="TOM LEFT0002" x="2560" y="720" width="1280" height="720"/>
	<SubTexture name="TOM LEFT0003" x="2560" y="720" width="1280" height="720"/>
	<SubTexture name="TOM LEFT0004" x="0" y="1440" width="1280" height="720"/>
	<SubTexture name="TOM LEFT0005" x="0" y="1440" width="1280" height="720"/>
	<SubTexture name="TOM LEFT0006" x="1280" y="1440" width="1280" height="720"/>
	<SubTexture name="TOM LEFT0007" x="1280" y="1440" width="1280" height="720"/>
	<SubTexture name="TOM LEFT0008" x="1280" y="1440" width="1280" height="720"/>
	<SubTexture name="TOM LEFT0009" x="1280" y="1440" width="1280" height="720"/>
	<SubTexture name="TOM LEFT0010" x="1280" y="1440" width="1280" height="720"/>
	<SubTexture name="TOM LEFT0011" x="1280" y="1440" width="1280" height="720"/>
	<SubTexture name="TOM LEFT0012" x="1280" y="1440" width="1280" height="720"/>
	<SubTexture name="TOM RIGHT0000" x="2560" y="1440" width="1280" height="720"/>
	<SubTexture name="TOM RIGHT0001" x="2560" y="1440" width="1280" height="720"/>
	<SubTexture name="TOM RIGHT0002" x="0" y="2160" width="1280" height="720"/>
	<SubTexture name="TOM RIGHT0003" x="0" y="2160" width="1280" height="720"/>
	<SubTexture name="TOM RIGHT0004" x="1280" y="2160" width="1280" height="720"/>
	<SubTexture name="TOM RIGHT0005" x="1280" y="2160" width="1280" height="720"/>
	<SubTexture name="TOM RIGHT0006" x="2560" y="2160" width="1280" height="720"/>
	<SubTexture name="TOM RIGHT0007" x="2560" y="2160" width="1280" height="720"/>
	<SubTexture name="TOM RIGHT0008" x="2560" y="2160" width="1280" height="720"/>
	<SubTexture name="TOM RIGHT0009" x="2560" y="2160" width="1280" height="720"/>
	<SubTexture name="TOM RIGHT0010" x="2560" y="2160" width="1280" height="720"/>
	<SubTexture name="TOM RIGHT0011" x="2560" y="2160" width="1280" height="720"/>
	<SubTexture name="TOM RIGHT0012" x="2560" y="2160" width="1280" height="720"/>
	<SubTexture name="TOM RIGHT0013" x="2560" y="2160" width="1280" height="720"/>
	<SubTexture name="TOM UP0000" x="0" y="2880" width="1280" height="720"/>
	<SubTexture name="TOM UP0001" x="0" y="2880" width="1280" height="720"/>
	<SubTexture name="TOM UP0002" x="1280" y="2880" width="1280" height="720"/>
	<SubTexture name="TOM UP0003" x="1280" y="2880" width="1280" height="720"/>
	<SubTexture name="TOM UP0004" x="2560" y="2880" width="1280" height="720"/>
	<SubTexture name="TOM UP0005" x="2560" y="2880" width="1280" height="720"/>
	<SubTexture name="TOM UP0006" x="0" y="3600" width="1280" height="720"/>
	<SubTexture name="TOM UP0007" x="0" y="3600" width="1280" height="720"/>
	<SubTexture name="TOM UP0008" x="0" y="3600" width="1280" height="720"/>
	<SubTexture name="TOM UP0009" x="0" y="3600" width="1280" height="720"/>
	<SubTexture name="TOM UP0010" x="0" y="3600" width="1280" height="720"/>
	<SubTexture name="TOM UP0011" x="0" y="3600" width="1280" height="720"/>
	<SubTexture name="TOM UP0012" x="0" y="3600" width="1280" height="720"/>
	<SubTexture name="TOM UP0013" x="0" y="3600" width="1280" height="720"/>
	<SubTexture name="TOM idle0000" x="1280" y="3600" width="1280" height="720"/>
	<SubTexture name="TOM idle0001" x="1280" y="3600" width="1280" height="720"/>
	<SubTexture name="TOM idle0002" x="2560" y="3600" width="1280" height="720"/>
	<SubTexture name="TOM idle0003" x="2560" y="3600" width="1280" height="720"/>
	<SubTexture name="TOM idle0004" x="0" y="4320" width="1280" height="720"/>
	<SubTexture name="TOM idle0005" x="0" y="4320" width="1280" height="720"/>
	<SubTexture name="TOM idle0006" x="1280" y="4320" width="1280" height="720"/>
	<SubTexture name="TOM idle0007" x="1280" y="4320" width="1280" height="720"/>
	<SubTexture name="TOM idle0008" x="2560" y="4320" width="1280" height="720"/>
	<SubTexture name="TOM idle0009" x="2560" y="4320" width="1280" height="720"/>
	<SubTexture name="TOM idle0010" x="0" y="5040" width="1280" height="720"/>
	<SubTexture name="TOM idle0011" x="0" y="5040" width="1280" height="720"/>
	<SubTexture name="TOM idle0012" x="0" y="5040" width="1280" height="720"/>
	<SubTexture name="TOM idle0013" x="0" y="5040" width="1280" height="720"/>
	<SubTexture name="TOM idle0014" x="0" y="5040" width="1280" height="720"/>
	<SubTexture name="TOM idle0015" x="0" y="5040" width="1280" height="720"/>
</TextureAtlas>
